smallpond/__init__.py
smallpond/common.py
smallpond/dataframe.py
smallpond/session.py
smallpond/utility.py
smallpond/worker.py
smallpond/contrib/__init__.py
smallpond/contrib/copy_table.py
smallpond/contrib/log_dataset.py
smallpond/contrib/warc.py
smallpond/execution/__init__.py
smallpond/execution/driver.py
smallpond/execution/executor.py
smallpond/execution/manager.py
smallpond/execution/scheduler.py
smallpond/execution/task.py
smallpond/execution/workqueue.py
smallpond/io/__init__.py
smallpond/io/arrow.py
smallpond/io/filesystem.py
smallpond/logical/__init__.py
smallpond/logical/dataset.py
smallpond/logical/node.py
smallpond/logical/optimizer.py
smallpond/logical/planner.py
smallpond/logical/udf.py
smallpond/platform/__init__.py
smallpond/platform/base.py
smallpond/platform/mpi.py
smallpond-0.15.0.dist-info/LICENSE
smallpond-0.15.0.dist-info/METADATA
smallpond-0.15.0.dist-info/WHEEL
smallpond-0.15.0.dist-info/top_level.txt
smallpond-0.15.0.dist-info/RECORD
