Metadata-Version: 2.2
Name: smallpond
Version: 0.15.0
Summary: A lightweight data processing framework built on DuckDB and shared file system.
Author: Runji Wang, Yiliang Xiong, Yiyuan Liu, Yuheng Zou, Yichao Zhang, Wenjun Gao, Wentao Zhang, Xiaotao Nie, Minghua Zhang, Zhewen Hao
Author-email: DeepSeek-AI <research@deepseek.com>
Project-URL: Homepage, https://github.com/deepseek-ai/smallpond
Keywords: distributed query processing,SQL,parquet
Requires-Python: >=3.8
License-File: LICENSE
Requires-Dist: duckdb>=1.2.0
Requires-Dist: pyarrow~=16.1.0
Requires-Dist: polars~=0.20.9
Requires-Dist: pandas>=1.3.4
Requires-Dist: plotly>=5.22.0
Requires-Dist: lxml>=4.9.3
Requires-Dist: cloudpickle>=2.0.0
Requires-Dist: zstandard>=0.22.0
Requires-Dist: loguru>=0.7.2
Requires-Dist: psutil>=5.9.8
Requires-Dist: GPUtil>=1.4.0
Requires-Dist: py-libnuma>=1.2
Requires-Dist: fsspec>=2023.12.2
Requires-Dist: ray[default]>=2.10.0
Requires-Dist: graphviz>=0.19.1
Provides-Extra: dev
Requires-Dist: coverage~=7.4.4; extra == "dev"
Requires-Dist: hypothesis~=6.100.0; extra == "dev"
Requires-Dist: pytest==8.2.1; extra == "dev"
Requires-Dist: pytest-cov==5.0.0; extra == "dev"
Requires-Dist: pytest-forked==1.6.0; extra == "dev"
Requires-Dist: pytest-xdist==3.6.1; extra == "dev"
Requires-Dist: pytest-timeout==2.3.1; extra == "dev"
Requires-Dist: pytest-benchmark==4.0.0; extra == "dev"
Requires-Dist: setproctitle==1.3.3; extra == "dev"
Requires-Dist: soupsieve~=2.5; extra == "dev"
Requires-Dist: setuptools-scm==8.1.0; extra == "dev"
Requires-Dist: packaging==24.2; extra == "dev"
Requires-Dist: jaraco.functools==4.1.0; extra == "dev"
Provides-Extra: docs
Requires-Dist: sphinx==7.1.2; extra == "docs"
Requires-Dist: pydata-sphinx-theme==0.14.4; extra == "docs"
Provides-Extra: warc
Requires-Dist: warcio>=1.7.4; extra == "warc"
Requires-Dist: beautifulsoup4>=4.12.2; extra == "warc"
